glb2png_i37c/__init__.py
glb2png_i37c/cli.py
glb2png-0.1.4.dist-info/METADATA
glb2png-0.1.4.dist-info/WHEEL
glb2png-0.1.4.dist-info/entry_points.txt
glb2png-0.1.4.dist-info/top_level.txt
glb2png-0.1.4.dist-info/RECORD
