Metadata-Version: 2.4
Name: glb2png
Version: 0.1.4
Summary: Convert GLB files to PNG previews
Author-email: imme37c_ <dodoimc@gmail.com>
Requires-Python: >=3.9
Requires-Dist: trimesh
Requires-Dist: pyrender
Requires-Dist: numpy
Requires-Dist: Pillow
Requires-Dist: click
